siren_rnai/__init__.py
siren_rnai/sirenXII.py
siren_rnai/siren_designVIII.py
siren_rnai/siren_masterV.py
siren_rnai/siren_plotIV.py
siren_rnai-0.1.4.dist-info/licenses/LICENSE
siren_rnai-0.1.4.dist-info/METADATA
siren_rnai-0.1.4.dist-info/WHEEL
siren_rnai-0.1.4.dist-info/entry_points.txt
siren_rnai-0.1.4.dist-info/top_level.txt
siren_rnai-0.1.4.dist-info/RECORD
