Metadata-Version: 2.4
Name: siren-rnai
Version: 0.1.4
Summary: SIREN: Suite for Intelligent RNAi design and Evaluation of Nucleotide sequences
Home-page: https://github.com/pablovargasmejia/SIREN
Author: Pablo Vargas Mejia
Author-email: 
License: GPLv3
Classifier: Programming Language :: Python :: 3
Classifier: License :: OSI Approved :: GNU General Public License v3 (GPLv3)
Classifier: Operating System :: OS Independent
Requires-Python: >=3.6
License-File: LICENSE
Requires-Dist: pandas
Requires-Dist: biopython
Requires-Dist: tqdm
Requires-Dist: primer3-py
Requires-Dist: matplotlib
Requires-Dist: numpy
Dynamic: author
Dynamic: classifier
Dynamic: description
Dynamic: description-content-type
Dynamic: home-page
Dynamic: license
Dynamic: license-file
Dynamic: requires-dist
Dynamic: requires-python
Dynamic: summary
